lib/__init__.py
lib/neopixel_spi_write.py
lib/neopixel_spidev.py
lib/pixelbuf.py
py_neopixel_spidev-1.0.0.dist-info/LICENSE
py_neopixel_spidev-1.0.0.dist-info/METADATA
py_neopixel_spidev-1.0.0.dist-info/WHEEL
py_neopixel_spidev-1.0.0.dist-info/top_level.txt
py_neopixel_spidev-1.0.0.dist-info/RECORD
