Metadata-Version: 2.1
Name: py-neopixel-spidev
Version: 1.0.0
Summary: A module that can be used to control WS2812 addressable         RGB LEDs via SPI on Linux devices using the generic Linux SPIdev driver
Home-page: https://github.com/fschrempf/py-neopixel-spidev
Author: Frieder Schrempf
Author-email: frieder.schrempf@kontron.de
License: UNKNOWN
Platform: UNKNOWN
Classifier: Programming Language :: Python :: 3
Classifier: License :: OSI Approved :: MIT License
Classifier: Operating System :: POSIX :: Linux
Requires-Python: >=3.6
